[
    {
        "id": 1,
        "category": "Sports & Leisure",
        "question": "Which team won the 2014 Fifa world cup?",
        "correctAnswer": "Germany",
        "incorrectAnswer1": "Spain",
        "incorrectAnswer2": "Brazil",
        "incorrectAnswer3": "France"
    },
    {
        "id": 2,
        "category": "Music",
        "question": "Who owns the record for the most streamed song on spotify?",
        "correctAnswer": "Ed Sheeran",
        "incorrectAnswer1": "The Weeknd",
        "incorrectAnswer2": "Drake",
        "incorrectAnswer3": "Zara Larsson"
    },
    {
        "id": 3,
        "category": "Movies & TV",
        "question": "In what year did the first Harry Potter movie release?",
        "correctAnswer": "2001",
        "incorrectAnswer1": "2005",
        "incorrectAnswer2": "2003",
        "incorrectAnswer3": "2002"
    },
    {
        "id": 4,
        "category": "Movies & TV",
        "question": "What is the name of Tony Sopranos daughter in the tv-series The Sopranos?",
        "correctAnswer": "Meadow",
        "incorrectAnswer1": "Carmela",
        "incorrectAnswer2": "Angelina",
        "incorrectAnswer3": "Skyler"
    },
    {
        "id": 5,
        "category": "Food & Drink",
        "question": "What does the italian dish name Caponata mean?",
        "correctAnswer": "Head food \/ main food",
        "incorrectAnswer1": "Without pasta",
        "incorrectAnswer2": "With pasta \/ with gluten",
        "incorrectAnswer3": "Non-traditional"
    },
    {
        "id": 6,
        "category": "Geography",
        "question": "Hur m\u00e5nga inv\u00e5nare har Malm\u00f6?",
        "correctAnswer": "353 000",
        "incorrectAnswer1": "260 000",
        "incorrectAnswer2": "400 000",
        "incorrectAnswer3": "500 000"
    }
]